README.md
setup.py
gpueater/__init__.py
gpueater/gpueater.py
gpueater.egg-info/PKG-INFO
gpueater.egg-info/SOURCES.txt
gpueater.egg-info/dependency_links.txt
gpueater.egg-info/not-zip-safe
gpueater.egg-info/requires.txt
gpueater.egg-info/top_level.txt