Metadata-Version: 1.1
Name: gpueater
Version: 1.5.0
Summary: GPUEater API console for python.
Home-page: https://github.com/aieater/gpueater_python
Author: Pegara, Inc.
Author-email: info@pegara.com
License: MIT
Keywords: gpu gpueater deeplearning eater cloud
Platform: UNKNOWN
Classifier: License :: OSI Approved :: MIT License
Classifier: Operating System :: OS Independent
Classifier: Programming Language :: Python :: 2
Classifier: Programming Language :: Python :: 2.7
Classifier: Programming Language :: Python :: 3
Classifier: Programming Language :: Python :: 3.4
Classifier: Programming Language :: Python :: 3.5
Classifier: Programming Language :: Python :: 3.6
